nt2/__init__.py
nt2/utils.py
nt2/cli/__init__.py
nt2/cli/__main__.py
nt2/cli/main.py
nt2/containers/__init__.py
nt2/containers/container.py
nt2/containers/data.py
nt2/containers/fields.py
nt2/containers/particles.py
nt2/containers/spectra.py
nt2/plotters/__init__.py
nt2/plotters/annotations.py
nt2/plotters/export.py
nt2/plotters/inspect.py
nt2/plotters/movie.py
nt2/plotters/particles.py
nt2/plotters/polar.py
nt2/readers/__init__.py
nt2/readers/adios2.py
nt2/readers/base.py
nt2/readers/hdf5.py
nt2py-1.3.0.dist-info/METADATA
nt2py-1.3.0.dist-info/WHEEL
nt2py-1.3.0.dist-info/entry_points.txt
nt2py-1.3.0.dist-info/licenses/LICENSE
nt2py-1.3.0.dist-info/RECORD
