Metadata-Version: 2.4
Name: nt2py
Version: 1.3.0
Summary: Post-processing & visualization toolkit for the Entity PIC code
Project-URL: Repository, https://github.com/entity-toolkit/nt2py
Author-email: Hayk <haykh.astro@gmail.com>
Maintainer-email: Hayk <haykh.astro@gmail.com>
License: BSD 3-Clause License
License-File: LICENSE
Classifier: Development Status :: 5 - Production/Stable
Classifier: Intended Audience :: Education
Classifier: Intended Audience :: Science/Research
Classifier: License :: OSI Approved :: BSD License
Classifier: Programming Language :: Python :: 3 :: Only
Classifier: Programming Language :: Python :: 3.8
Classifier: Programming Language :: Python :: 3.9
Classifier: Programming Language :: Python :: 3.10
Classifier: Programming Language :: Python :: 3.11
Classifier: Programming Language :: Python :: 3.12
Classifier: Programming Language :: Python :: 3.13
Classifier: Topic :: Scientific/Engineering :: Astronomy
Classifier: Topic :: Scientific/Engineering :: Physics
Requires-Python: >=3.8
Requires-Dist: adios2
Requires-Dist: bokeh
Requires-Dist: contourpy
Requires-Dist: dask[complete]
Requires-Dist: matplotlib
Requires-Dist: numpy
Requires-Dist: scipy
Requires-Dist: tqdm
Requires-Dist: typer
Requires-Dist: types-setuptools
Requires-Dist: xarray
Provides-Extra: hdf5
Requires-Dist: h5py; extra == 'hdf5'
